{"approved_at_utc": null, "selftext": "", "author_fullname": "t2_1itbstge", "saved": false, "mod_reason_title": null, "gilded": 0, "clicked": false, "title": "\u201cWSB doesn\u2019t touch garbage like that\u201d", "link_flair_richtext": [{"e": "text", "t": "Satire"}], "subreddit_name_prefixed": "r/wallstreetbets", "hidden": false, "pwls": 0, "link_flair_css_class": "satire", "downs": 0, "thumbnail_height": 140, "top_awarded_type": null, "hide_score": false, "name": "t3_kdzlvr", "quarantine": false, "link_flair_text_color": "light", "upvote_ratio": 0.98, "author_flair_background_color": null, "subreddit_type": "public", "ups": 1005, "total_awards_received": 3, "media_embed": {}, "thumbnail_width": 140, "author_flair_template_id": null, "is_original_content": false, "user_reports": [], "secure_media": null, "is_reddit_media_domain": true, "is_meta": false, "category": null, "secure_media_embed": {}, "link_flair_text": "Satire", "can_mod_post": false, "score": 1005, "approved_by": null, "author_premium": false, "thumbnail": "https://b.thumbs.redditmedia.com/6sREWqIVrpeg6r0MZq5dJuW_IfZs0lNpqlQkqLCNKTc.jpg", "edited": false, "author_flair_css_class": null, "author_flair_richtext": [], "gildings": {}, "post_hint": "image", "content_categories": null, "is_self": false, "mod_note": null, "created": 1608111961.0, "link_flair_type": "richtext", "wls": 0, "removed_by_category": null, "banned_by": null, "author_flair_type": "text", "domain": "i.redd.it", "allow_live_comments": false, "selftext_html": null, "likes": null, "suggested_sort": "confidence", "banned_at_utc": null, "url_overridden_by_dest": "https://i.redd.it/6a4hoz2cfg561.jpg", "view_count": null, "archived": false, "no_follow": false, "is_crosspostable": false, "pinned": false, "over_18": false, "preview": {"images": [{"source": {"url": "https://preview.redd.it/6a4hoz2cfg561.jpg?auto=webp&s=2c98c84faf80ea1d6cab92f7834f0ebdcc767f0d", "width": 750, "height": 1286}, "resolutions": [{"url": "https://preview.redd.it/6a4hoz2cfg561.jpg?width=108&crop=smart&auto=webp&s=a2bcf11eedf8181f565186023122805be2c55844", "width": 108, "height": 185}, {"url": "https://preview.redd.it/6a4hoz2cfg561.jpg?width=216&crop=smart&auto=webp&s=41489261f726b582c4962848f3155662056a140e", "width": 216, "height": 370}, {"url": "https://preview.redd.it/6a4hoz2cfg561.jpg?width=320&crop=smart&auto=webp&s=415bb60f33a2252131a86ab51e325c275dba7e48", "width": 320, "height": 548}, {"url": "https://preview.redd.it/6a4hoz2cfg561.jpg?width=640&crop=smart&auto=webp&s=2abeaa4cc8afff97a35b929e133005738c3e9f0e", "width": 640, "height": 1097}], "variants": {}, "id": "sM7NDhwSqoEpSw6UdQ83WWggquU0p-b0DQV-CSrbVB8"}], "enabled": true}, "all_awardings": [{"giver_coin_reward": null, "subreddit_id": null, "is_new": false, "days_of_drip_extension": 0, "coin_price": 300, "id": "award_28e8196b-d4e9-45bc-b612-cd4c7d3ed4b3", "penny_donate": null, "award_sub_type": "GLOBAL", "coin_reward": 0, "icon_url": "https://i.redd.it/award_images/t5_q0gj4/9fmmyy3c68361_RocketLikeSanta.png", "days_of_premium": 0, "tiers_by_required_awardings": null, "resized_icons": [{"url": "https://preview.redd.it/award_images/t5_q0gj4/9fmmyy3c68361_RocketLikeSanta.png?width=16&height=16&auto=webp&s=24fc4d912e595c3fed2ce0deef1c13f70df56056", "width": 16, "height": 16}, {"url": "https://preview.redd.it/award_images/t5_q0gj4/9fmmyy3c68361_RocketLikeSanta.png?width=32&height=32&auto=webp&s=f9d869602e0d8b719186cc603864a42699e5c96e", "width": 32, "height": 32}, {"url": "https://preview.redd.it/award_images/t5_q0gj4/9fmmyy3c68361_RocketLikeSanta.png?width=48&height=48&auto=webp&s=b223ac8fdd206b683b840c2782307c3f01b04fb7", "width": 48, "height": 48}, {"url": "https://preview.redd.it/award_images/t5_q0gj4/9fmmyy3c68361_RocketLikeSanta.png?width=64&height=64&auto=webp&s=a0b840c6ecdee904012a6c53c40194733b72bca8", "width": 64, "height": 64}, {"url": "https://preview.redd.it/award_images/t5_q0gj4/9fmmyy3c68361_RocketLikeSanta.png?width=128&height=128&auto=webp&s=b2e2ca67e067f82ff9b4ea1fe1b39395ca622894", "width": 128, "height": 128}], "icon_width": 2048, "static_icon_width": 2048, "start_date": null, "is_enabled": true, "awardings_required_to_grant_benefits": null, "description": "When an upvote just isn't enough, smash the Rocket Like.", "end_date": null, "subreddit_coin_reward": 0, "count": 1, "static_icon_height": 2048, "name": "Rocket Like", "resized_static_icons": [{"url": "https://preview.redd.it/award_images/t5_q0gj4/9fmmyy3c68361_RocketLikeSanta.png?width=16&height=16&auto=webp&s=24fc4d912e595c3fed2ce0deef1c13f70df56056", "width": 16, "height": 16}, {"url": "https://preview.redd.it/award_images/t5_q0gj4/9fmmyy3c68361_RocketLikeSanta.png?width=32&height=32&auto=webp&s=f9d869602e0d8b719186cc603864a42699e5c96e", "width": 32, "height": 32}, {"url": "https://preview.redd.it/award_images/t5_q0gj4/9fmmyy3c68361_RocketLikeSanta.png?width=48&height=48&auto=webp&s=b223ac8fdd206b683b840c2782307c3f01b04fb7", "width": 48, "height": 48}, {"url": "https://preview.redd.it/award_images/t5_q0gj4/9fmmyy3c68361_RocketLikeSanta.png?width=64&height=64&auto=webp&s=a0b840c6ecdee904012a6c53c40194733b72bca8", "width": 64, "height": 64}, {"url": "https://preview.redd.it/award_images/t5_q0gj4/9fmmyy3c68361_RocketLikeSanta.png?width=128&height=128&auto=webp&s=b2e2ca67e067f82ff9b4ea1fe1b39395ca622894", "width": 128, "height": 128}], "icon_format": null, "icon_height": 2048, "penny_price": null, "award_type": "global", "static_icon_url": "https://i.redd.it/award_images/t5_q0gj4/9fmmyy3c68361_RocketLikeSanta.png"}, {"giver_coin_reward": 0, "subreddit_id": null, "is_new": false, "days_of_drip_extension": 0, "coin_price": 80, "id": "award_8352bdff-3e03-4189-8a08-82501dd8f835", "penny_donate": 0, "award_sub_type": "GLOBAL", "coin_reward": 0, "icon_url": "https://i.redd.it/award_images/t5_q0gj4/fpm0r5ryq1361_PolarHugs.png", "days_of_premium": 0, "tiers_by_required_awardings": null, "resized_icons": [{"url": "https://preview.redd.it/award_images/t5_q0gj4/fpm0r5ryq1361_PolarHugs.png?width=16&height=16&auto=webp&s=69997ace3ef4ffc099b81d774c2c8f1530602875", "width": 16, "height": 16}, {"url": "https://preview.redd.it/award_images/t5_q0gj4/fpm0r5ryq1361_PolarHugs.png?width=32&height=32&auto=webp&s=e9519d1999ef9dce5c8a9f59369cb92f52d95319", "width": 32, "height": 32}, {"url": "https://preview.redd.it/award_images/t5_q0gj4/fpm0r5ryq1361_PolarHugs.png?width=48&height=48&auto=webp&s=f076c6434fb2d2f9075991810fd845c40fa73fc6", "width": 48, "height": 48}, {"url": "https://preview.redd.it/award_images/t5_q0gj4/fpm0r5ryq1361_PolarHugs.png?width=64&height=64&auto=webp&s=85527145e0c4b754306a30df29e584fd16187636", "width": 64, "height": 64}, {"url": "https://preview.redd.it/award_images/t5_q0gj4/fpm0r5ryq1361_PolarHugs.png?width=128&height=128&auto=webp&s=b8843cdf82c3b741d7af057c14076dcd2621e811", "width": 128, "height": 128}], "icon_width": 2048, "static_icon_width": 2048, "start_date": null, "is_enabled": true, "awardings_required_to_grant_benefits": null, "description": "Everything is better with a good hug", "end_date": null, "subreddit_coin_reward": 0, "count": 2, "static_icon_height": 2048, "name": "Hugz", "resized_static_icons": [{"url": "https://preview.redd.it/award_images/t5_q0gj4/fpm0r5ryq1361_PolarHugs.png?width=16&height=16&auto=webp&s=69997ace3ef4ffc099b81d774c2c8f1530602875", "width": 16, "height": 16}, {"url": "https://preview.redd.it/award_images/t5_q0gj4/fpm0r5ryq1361_PolarHugs.png?width=32&height=32&auto=webp&s=e9519d1999ef9dce5c8a9f59369cb92f52d95319", "width": 32, "height": 32}, {"url": "https://preview.redd.it/award_images/t5_q0gj4/fpm0r5ryq1361_PolarHugs.png?width=48&height=48&auto=webp&s=f076c6434fb2d2f9075991810fd845c40fa73fc6", "width": 48, "height": 48}, {"url": "https://preview.redd.it/award_images/t5_q0gj4/fpm0r5ryq1361_PolarHugs.png?width=64&height=64&auto=webp&s=85527145e0c4b754306a30df29e584fd16187636", "width": 64, "height": 64}, {"url": "https://preview.redd.it/award_images/t5_q0gj4/fpm0r5ryq1361_PolarHugs.png?width=128&height=128&auto=webp&s=b8843cdf82c3b741d7af057c14076dcd2621e811", "width": 128, "height": 128}], "icon_format": "PNG", "icon_height": 2048, "penny_price": 0, "award_type": "global", "static_icon_url": "https://i.redd.it/award_images/t5_q0gj4/fpm0r5ryq1361_PolarHugs.png"}], "awarders": [], "media_only": false, "link_flair_template_id": "144ac78c-4ef5-11e9-a41b-0e1478d1aeb0", "can_gild": false, "spoiler": false, "locked": false, "author_flair_text": null, "treatment_tags": [], "visited": false, "removed_by": null, "num_reports": null, "distinguished": null, "subreddit_id": "t5_2th52", "mod_reason_by": null, "removal_reason": null, "link_flair_background_color": "#ff4500", "id": "kdzlvr", "is_robot_indexable": true, "report_reasons": null, "author": {"name": "Larrysfuneral", "fullname": "t2_1itbstge"}, "discussion_type": null, "num_comments": 106, "send_replies": true, "whitelist_status": "no_ads", "contest_mode": false, "mod_reports": [], "author_patreon_flair": false, "author_flair_text_color": null, "permalink": "/r/wallstreetbets/comments/kdzlvr/wsb_doesnt_touch_garbage_like_that/", "parent_whitelist_status": "no_ads", "stickied": false, "url": "https://i.redd.it/6a4hoz2cfg561.jpg", "subreddit_subscribers": 1708879, "created_utc": 1608083161.0, "num_crossposts": 0, "media": null, "is_video": false, "comment_limit": 2048, "comment_sort": "confidence", "comments": [{"total_awards_received": 0, "approved_at_utc": null, "comment_type": null, "awarders": [], "mod_reason_by": null, "banned_by": null, "ups": 461, "author_flair_type": "text", "removal_reason": null, "link_id": "t3_kdzlvr", "author_flair_template_id": null, "likes": null, "user_reports": [], "saved": false, "id": "gfzjqt9", "banned_at_utc": null, "mod_reason_title": null, "gilded": 0, "archived": false, "no_follow": false, "author": {"name": "AccidentalHacker39", "fullname": "t2_2r6icuxc"}, "can_mod_post": false, "send_replies": true, "parent_id": "t3_kdzlvr", "score": 461, "author_fullname": "t2_2r6icuxc", "report_reasons": null, "approved_by": null, "all_awardings": [], "subreddit_id": "t5_2th52", "body": "We work for Doordash, we know it's a pile of steaming hot garbage.", "edited": false, "downs": 0, "author_flair_css_class": null, "is_submitter": false, "collapsed": false, "author_flair_richtext": [], "author_patreon_flair": false, "body_html": "<div class=\"md\"><p>We work for Doordash, we know it&#39;s a pile of steaming hot garbage.</p>\n</div>", "gildings": {}, "collapsed_reason": null, "associated_award": null, "stickied": false, "author_premium": false, "subreddit_type": "public", "can_gild": true, "top_awarded_type": null, "author_flair_text_color": null, "score_hidden": false, "permalink": "/r/wallstreetbets/comments/kdzlvr/wsb_doesnt_touch_garbage_like_that/gfzjqt9/", "num_reports": null, "locked": false, "name": "t1_gfzjqt9", "created": 1608112098.0, "author_flair_text": null, "treatment_tags": [], "created_utc": 1608083298.0, "subreddit_name_prefixed": "r/wallstreetbets", "controversiality": 0, "depth": 0, "author_flair_background_color": null, "collapsed_because_crowd_control": null, "mod_reports": [], "mod_note": null, "distinguished": null, "replies": [{"total_awards_received": 0, "approved_at_utc": null, "comment_type": null, "awarders": [], "mod_reason_by": null, "banned_by": null, "ups": 208, "author_flair_type": "text", "removal_reason": null, "link_id": "t3_kdzlvr", "author_flair_template_id": null, "likes": null, "user_reports": [], "saved": false, "id": "gfzjuwl", "banned_at_utc": null, "mod_reason_title": null, "gilded": 0, "archived": false, "no_follow": false, "author": {"name": "Larrysfuneral", "fullname": "t2_1itbstge"}, "can_mod_post": false, "send_replies": true, "parent_id": "t1_gfzjqt9", "score": 208, "author_fullname": "t2_1itbstge", "report_reasons": null, "approved_by": null, "all_awardings": [], "subreddit_id": "t5_2th52", "collapsed": false, "body": "Door dash \u201cHey take this 10 mile order for 3.25$\u201d", "edited": false, "author_flair_css_class": null, "is_submitter": true, "downs": 0, "author_flair_richtext": [], "author_patreon_flair": false, "body_html": "<div class=\"md\"><p>Door dash \u201cHey take this 10 mile order for 3.25$\u201d</p>\n</div>", "gildings": {}, "collapsed_reason": null, "associated_award": null, "stickied": false, "author_premium": false, "subreddit_type": "public", "can_gild": true, "top_awarded_type": null, "author_flair_text_color": null, "score_hidden": false, "permalink": "/r/wallstreetbets/comments/kdzlvr/wsb_doesnt_touch_garbage_like_that/gfzjuwl/", "num_reports": null, "locked": false, "name": "t1_gfzjuwl", "created": 1608112161.0, "author_flair_text": null, "treatment_tags": [], "created_utc": 1608083361.0, "subreddit_name_prefixed": "r/wallstreetbets", "controversiality": 0, "depth": 1, "author_flair_background_color": null, "collapsed_because_crowd_control": null, "mod_reports": [], "mod_note": null, "distinguished": null, "replies": [{"total_awards_received": 0, "approved_at_utc": null, "comment_type": null, "awarders": [], "mod_reason_by": null, "banned_by": null, "ups": 109, "author_flair_type": "richtext", "removal_reason": null, "link_id": "t3_kdzlvr", "author_flair_template_id": null, "likes": null, "user_reports": [], "saved": false, "id": "gfzqgyv", "banned_at_utc": null, "mod_reason_title": null, "gilded": 0, "archived": false, "no_follow": false, "author": {"name": "MawTooth", "fullname": "t2_7jr06077"}, "can_mod_post": false, "created_utc": 1608087058.0, "send_replies": true, "parent_id": "t1_gfzjuwl", "score": 109, "author_fullname": "t2_7jr06077", "report_reasons": null, "approved_by": null, "all_awardings": [], "subreddit_id": "t5_2th52", "body": "Take this Walmart order of 82 items for $4.26, oh and it's an express order so you have to go into the store and push out the car and load it yourself... And also it's 10 miles.", "edited": false, "author_flair_css_class": null, "is_submitter": false, "downs": 0, "author_flair_richtext": [{"e": "text", "t": "\u001b200918:3:1"}], "author_patreon_flair": false, "body_html": "<div class=\"md\"><p>Take this Walmart order of 82 items for $4.26, oh and it&#39;s an express order so you have to go into the store and push out the car and load it yourself... And also it&#39;s 10 miles.</p>\n</div>", "gildings": {}, "collapsed_reason": null, "associated_award": null, "stickied": false, "author_premium": false, "subreddit_type": "public", "can_gild": true, "top_awarded_type": null, "author_flair_text_color": "dark", "score_hidden": false, "permalink": "/r/wallstreetbets/comments/kdzlvr/wsb_doesnt_touch_garbage_like_that/gfzqgyv/", "num_reports": null, "locked": false, "name": "t1_gfzqgyv", "created": 1608115858.0, "author_flair_text": "\u001b200918:3:1", "treatment_tags": [], "collapsed": false, "subreddit_name_prefixed": "r/wallstreetbets", "controversiality": 0, "depth": 2, "author_flair_background_color": "", "collapsed_because_crowd_control": null, "mod_reports": [], "mod_note": null, "distinguished": null, "replies": [{"total_awards_received": 0, "approved_at_utc": null, "comment_type": null, "awarders": [], "mod_reason_by": null, "banned_by": null, "ups": 43, "author_flair_type": "text", "removal_reason": null, "link_id": "t3_kdzlvr", "author_flair_template_id": null, "likes": null, "user_reports": [], "saved": false, "id": "gfzqxg3", "banned_at_utc": null, "mod_reason_title": null, "gilded": 0, "archived": false, "no_follow": false, "author": {"name": "Larrysfuneral", "fullname": "t2_1itbstge"}, "can_mod_post": false, "send_replies": true, "parent_id": "t1_gfzqgyv", "score": 43, "author_fullname": "t2_1itbstge", "report_reasons": null, "approved_by": null, "all_awardings": [], "subreddit_id": "t5_2th52", "body": "Fuck Walmart, bullish", "edited": false, "downs": 0, "author_flair_css_class": null, "is_submitter": true, "collapsed": false, "author_flair_richtext": [], "author_patreon_flair": false, "body_html": "<div class=\"md\"><p>Fuck Walmart, bullish</p>\n</div>", "gildings": {}, "collapsed_reason": null, "associated_award": null, "stickied": false, "author_premium": false, "subreddit_type": "public", "can_gild": true, "top_awarded_type": null, "author_flair_text_color": null, "score_hidden": false, "permalink": "/r/wallstreetbets/comments/kdzlvr/wsb_doesnt_touch_garbage_like_that/gfzqxg3/", "num_reports": null, "locked": false, "name": "t1_gfzqxg3", "created": 1608116115.0, "author_flair_text": null, "treatment_tags": [], "created_utc": 1608087315.0, "subreddit_name_prefixed": "r/wallstreetbets", "controversiality": 0, "depth": 3, "author_flair_background_color": null, "collapsed_because_crowd_control": null, "mod_reports": [], "mod_note": null, "distinguished": null, "replies": [{"total_awards_received": 0, "approved_at_utc": null, "comment_type": null, "awarders": [], "mod_reason_by": null, "banned_by": null, "ups": 16, "author_flair_type": "richtext", "removal_reason": null, "link_id": "t3_kdzlvr", "author_flair_template_id": null, "likes": null, "user_reports": [], "saved": false, "id": "gg0bpsm", "banned_at_utc": null, "mod_reason_title": null, "gilded": 0, "archived": false, "no_follow": false, "author": {"name": "MawTooth", "fullname": "t2_7jr06077"}, "can_mod_post": false, "send_replies": true, "parent_id": "t1_gfzqxg3", "score": 16, "author_fullname": "t2_7jr06077", "report_reasons": null, "approved_by": null, "all_awardings": [], "subreddit_id": "t5_2th52", "collapsed": false, "body": "They used be be orders to jump on. I pass on that as much as I can now. Post-order tips nearly never happen now.", "edited": 1608101501.0, "author_flair_css_class": null, "is_submitter": false, "downs": 0, "author_flair_richtext": [{"e": "text", "t": "\u001b200918:3:1"}], "author_patreon_flair": false, "body_html": "<div class=\"md\"><p>They used be be orders to jump on. I pass on that as much as I can now. Post-order tips nearly never happen now.</p>\n</div>", "gildings": {}, "collapsed_reason": null, "associated_award": null, "stickied": false, "author_premium": false, "subreddit_type": "public", "can_gild": true, "top_awarded_type": null, "author_flair_text_color": "dark", "score_hidden": false, "permalink": "/r/wallstreetbets/comments/kdzlvr/wsb_doesnt_touch_garbage_like_that/gg0bpsm/", "num_reports": null, "locked": false, "name": "t1_gg0bpsm", "created": 1608130115.0, "author_flair_text": "\u001b200918:3:1", "treatment_tags": [], "created_utc": 1608101315.0, "subreddit_name_prefixed": "r/wallstreetbets", "controversiality": 0, "depth": 4, "author_flair_background_color": "", "collapsed_because_crowd_control": null, "mod_reports": [], "mod_note": null, "distinguished": null, "replies": [{"total_awards_received": 0, "approved_at_utc": null, "comment_type": null, "awarders": [], "mod_reason_by": null, "banned_by": null, "ups": 15, "author_flair_type": "text", "removal_reason": null, "link_id": "t3_kdzlvr", "author_flair_template_id": null, "likes": null, "user_reports": [], "saved": false, "id": "gg0buva", "banned_at_utc": null, "mod_reason_title": null, "gilded": 0, "archived": false, "no_follow": false, "author": {"name": "Larrysfuneral", "fullname": "t2_1itbstge"}, "can_mod_post": false, "created_utc": 1608101432.0, "send_replies": true, "parent_id": "t1_gg0bpsm", "score": 15, "author_fullname": "t2_1itbstge", "report_reasons": null, "approved_by": null, "all_awardings": [], "subreddit_id": "t5_2th52", "body": "I\u2019ve seen that, they really don\u2019t give a fuck about workers.", "edited": false, "author_flair_css_class": null, "is_submitter": true, "downs": 0, "author_flair_richtext": [], "author_patreon_flair": false, "body_html": "<div class=\"md\"><p>I\u2019ve seen that, they really don\u2019t give a fuck about workers.</p>\n</div>", "gildings": {}, "collapsed_reason": null, "associated_award": null, "stickied": false, "author_premium": false, "subreddit_type": "public", "can_gild": true, "top_awarded_type": null, "author_flair_text_color": null, "score_hidden": false, "permalink": "/r/wallstreetbets/comments/kdzlvr/wsb_doesnt_touch_garbage_like_that/gg0buva/", "num_reports": null, "locked": false, "name": "t1_gg0buva", "created": 1608130232.0, "author_flair_text": null, "treatment_tags": [], "collapsed": false, "subreddit_name_prefixed": "r/wallstreetbets", "controversiality": 0, "depth": 5, "author_flair_background_color": null, "collapsed_because_crowd_control": null, "mod_reports": [], "mod_note": null, "distinguished": null, "replies": [{"total_awards_received": 0, "approved_at_utc": null, "comment_type": null, "awarders": [], "mod_reason_by": null, "banned_by": null, "ups": 13, "author_flair_type": "richtext", "removal_reason": null, "link_id": "t3_kdzlvr", "author_flair_template_id": null, "likes": null, "user_reports": [], "saved": false, "id": "gg0cqg5", "banned_at_utc": null, "mod_reason_title": null, "gilded": 0, "archived": false, "no_follow": false, "author": {"name": "MawTooth", "fullname": "t2_7jr06077"}, "can_mod_post": false, "send_replies": true, "parent_id": "t1_gg0buva", "score": 13, "author_fullname": "t2_7jr06077", "report_reasons": null, "approved_by": null, "all_awardings": [], "subreddit_id": "t5_2th52", "body": "Also, I can't complain too much.... It's side gig to supplement the consumer cost of my depression that was getting better before COVID. In the before times it was a vessel to get to a house down payment quicker. Oh balls.... At least I'm learning from the pros on WSB.. AKA Wallstreet Strategies Bureau....", "edited": false, "downs": 0, "author_flair_css_class": null, "is_submitter": false, "collapsed": false, "author_flair_richtext": [{"e": "text", "t": "\u001b200918:3:1"}], "author_patreon_flair": false, "body_html": "<div class=\"md\"><p>Also, I can&#39;t complain too much.... It&#39;s side gig to supplement the consumer cost of my depression that was getting better before COVID. In the before times it was a vessel to get to a house down payment quicker. Oh balls.... At least I&#39;m learning from the pros on WSB.. AKA Wallstreet Strategies Bureau....</p>\n</div>", "gildings": {}, "collapsed_reason": null, "associated_award": null, "stickied": false, "author_premium": false, "subreddit_type": "public", "can_gild": true, "top_awarded_type": null, "author_flair_text_color": "dark", "score_hidden": false, "permalink": "/r/wallstreetbets/comments/kdzlvr/wsb_doesnt_touch_garbage_like_that/gg0cqg5/", "num_reports": null, "locked": false, "name": "t1_gg0cqg5", "created": 1608130982.0, "author_flair_text": "\u001b200918:3:1", "treatment_tags": [], "created_utc": 1608102182.0, "subreddit_name_prefixed": "r/wallstreetbets", "controversiality": 0, "depth": 6, "author_flair_background_color": "", "collapsed_because_crowd_control": null, "mod_reports": [], "mod_note": null, "distinguished": null, "replies": [{"total_awards_received": 0, "approved_at_utc": null, "comment_type": null, "awarders": [], "mod_reason_by": null, "banned_by": null, "ups": 13, "author_flair_type": "text", "removal_reason": null, "link_id": "t3_kdzlvr", "author_flair_template_id": null, "likes": null, "user_reports": [], "saved": false, "id": "gg0dyfr", "banned_at_utc": null, "mod_reason_title": null, "gilded": 0, "archived": false, "no_follow": false, "author": {"name": "Larrysfuneral", "fullname": "t2_1itbstge"}, "can_mod_post": false, "send_replies": true, "parent_id": "t1_gg0cqg5", "score": 13, "author_fullname": "t2_1itbstge", "report_reasons": null, "approved_by": null, "all_awardings": [], "subreddit_id": "t5_2th52", "collapsed": false, "body": "Keep your head up, the good thing is that you\u2019re moving forward", "edited": false, "author_flair_css_class": null, "is_submitter": true, "downs": 0, "author_flair_richtext": [], "author_patreon_flair": false, "body_html": "<div class=\"md\"><p>Keep your head up, the good thing is that you\u2019re moving forward</p>\n</div>", "gildings": {}, "collapsed_reason": null, "associated_award": null, "stickied": false, "author_premium": false, "subreddit_type": "public", "can_gild": true, "top_awarded_type": null, "author_flair_text_color": null, "score_hidden": false, "permalink": "/r/wallstreetbets/comments/kdzlvr/wsb_doesnt_touch_garbage_like_that/gg0dyfr/", "num_reports": null, "locked": false, "name": "t1_gg0dyfr", "created": 1608132052.0, "author_flair_text": null, "treatment_tags": [], "created_utc": 1608103252.0, "subreddit_name_prefixed": "r/wallstreetbets", "controversiality": 0, "depth": 7, "author_flair_background_color": null, "collapsed_because_crowd_control": null, "mod_reports": [], "mod_note": null, "distinguished": null, "replies": []}, {"total_awards_received": 0, "approved_at_utc": null, "comment_type": null, "awarders": [], "mod_reason_by": null, "banned_by": null, "ups": 4, "author_flair_type": "text", "removal_reason": null, "link_id": "t3_kdzlvr", "author_flair_template_id": null, "likes": null, "user_reports": [], "saved": false, "id": "gg0kel4", "banned_at_utc": null, "mod_reason_title": null, "gilded": 0, "archived": false, "no_follow": false, "author": {"name": "wheresastroworld", "fullname": "t2_1jxzt0ce"}, "can_mod_post": false, "send_replies": true, "parent_id": "t1_gg0cqg5", "score": 4, "author_fullname": "t2_1jxzt0ce", "report_reasons": null, "approved_by": null, "all_awardings": [], "subreddit_id": "t5_2th52", "collapsed": false, "body": "that would be WSSB. however the fact that you can\u2019t form a simple acronym shows you belong here", "edited": false, "author_flair_css_class": null, "is_submitter": false, "downs": 0, "author_flair_richtext": [], "author_patreon_flair": false, "body_html": "<div class=\"md\"><p>that would be WSSB. however the fact that you can\u2019t form a simple acronym shows you belong here</p>\n</div>", "gildings": {}, "collapsed_reason": null, "associated_award": null, "stickied": false, "author_premium": false, "subreddit_type": "public", "can_gild": true, "top_awarded_type": null, "author_flair_text_color": null, "score_hidden": false, "permalink": "/r/wallstreetbets/comments/kdzlvr/wsb_doesnt_touch_garbage_like_that/gg0kel4/", "num_reports": null, "locked": false, "name": "t1_gg0kel4", "created": 1608138048.0, "author_flair_text": null, "treatment_tags": [], "created_utc": 1608109248.0, "subreddit_name_prefixed": "r/wallstreetbets", "controversiality": 0, "depth": 7, "author_flair_background_color": null, "collapsed_because_crowd_control": null, "mod_reports": [], "mod_note": null, "distinguished": null, "replies": []}]}]}, {"total_awards_received": 0, "approved_at_utc": null, "comment_type": null, "awarders": [], "mod_reason_by": null, "banned_by": null, "ups": 1, "author_flair_type": "text", "removal_reason": null, "link_id": "t3_kdzlvr", "author_flair_template_id": null, "likes": null, "user_reports": [], "saved": false, "id": "gg238bz", "banned_at_utc": null, "mod_reason_title": null, "gilded": 0, "archived": false, "no_follow": true, "author": {"name": "Celtic_Legend", "fullname": "t2_14uvb0"}, "can_mod_post": false, "created_utc": 1608144790.0, "send_replies": true, "parent_id": "t1_gg0bpsm", "score": 1, "author_fullname": "t2_14uvb0", "report_reasons": null, "approved_by": null, "all_awardings": [], "subreddit_id": "t5_2th52", "body": "I cant even figure out how to do post order tips on doordash", "edited": false, "author_flair_css_class": null, "is_submitter": false, "downs": 0, "author_flair_richtext": [], "author_patreon_flair": false, "body_html": "<div class=\"md\"><p>I cant even figure out how to do post order tips on doordash</p>\n</div>", "gildings": {}, "collapsed_reason": null, "associated_award": null, "stickied": false, "author_premium": false, "subreddit_type": "public", "can_gild": true, "top_awarded_type": null, "author_flair_text_color": null, "score_hidden": false, "permalink": "/r/wallstreetbets/comments/kdzlvr/wsb_doesnt_touch_garbage_like_that/gg238bz/", "num_reports": null, "locked": false, "name": "t1_gg238bz", "created": 1608173590.0, "author_flair_text": null, "treatment_tags": [], "collapsed": false, "subreddit_name_prefixed": "r/wallstreetbets", "controversiality": 0, "depth": 5, "author_flair_background_color": null, "collapsed_because_crowd_control": null, "mod_reports": [], "mod_note": null, "distinguished": null, "replies": []}]}]}]}, {"total_awards_received": 0, "approved_at_utc": null, "comment_type": null, "awarders": [], "mod_reason_by": null, "banned_by": null, "ups": 4, "author_flair_type": "text", "removal_reason": null, "link_id": "t3_kdzlvr", "author_flair_template_id": null, "likes": null, "user_reports": [], "saved": false, "id": "gg0r5wo", "banned_at_utc": null, "mod_reason_title": null, "gilded": 0, "archived": false, "no_follow": false, "author": {"name": "SpyThyGuy", "fullname": "t2_7kdzqz15"}, "can_mod_post": false, "created_utc": 1608116239.0, "send_replies": true, "parent_id": "t1_gfzjuwl", "score": 4, "author_fullname": "t2_7kdzqz15", "report_reasons": null, "approved_by": null, "all_awardings": [], "subreddit_id": "t5_2th52", "body": "\u201cAdvanced routing algorithms\u201d", "edited": false, "author_flair_css_class": null, "is_submitter": false, "downs": 0, "author_flair_richtext": [], "author_patreon_flair": false, "body_html": "<div class=\"md\"><p>\u201cAdvanced routing algorithms\u201d</p>\n</div>", "gildings": {}, "collapsed_reason": null, "associated_award": null, "stickied": false, "author_premium": true, "subreddit_type": "public", "can_gild": true, "top_awarded_type": null, "author_flair_text_color": null, "score_hidden": false, "permalink": "/r/wallstreetbets/comments/kdzlvr/wsb_doesnt_touch_garbage_like_that/gg0r5wo/", "num_reports": null, "locked": false, "name": "t1_gg0r5wo", "created": 1608145039.0, "author_flair_text": null, "treatment_tags": [], "collapsed": false, "subreddit_name_prefixed": "r/wallstreetbets", "controversiality": 0, "depth": 2, "author_flair_background_color": null, "collapsed_because_crowd_control": null, "mod_reports": [], "mod_note": null, "distinguished": null, "replies": [{"total_awards_received": 0, "approved_at_utc": null, "comment_type": null, "awarders": [], "mod_reason_by": null, "banned_by": null, "ups": 5, "author_flair_type": "text", "removal_reason": null, "link_id": "t3_kdzlvr", "author_flair_template_id": null, "likes": null, "user_reports": [], "saved": false, "id": "gg12mxu", "banned_at_utc": null, "mod_reason_title": null, "gilded": 0, "archived": false, "no_follow": false, "author": {"name": "torontodeveloper", "fullname": "t2_8z7nw"}, "can_mod_post": false, "send_replies": true, "parent_id": "t1_gg0r5wo", "score": 5, "author_fullname": "t2_8z7nw", "report_reasons": null, "approved_by": null, "all_awardings": [], "subreddit_id": "t5_2th52", "body": "You misspelled \"Google maps directions API\"", "edited": false, "downs": 0, "author_flair_css_class": null, "is_submitter": false, "collapsed": false, "author_flair_richtext": [], "author_patreon_flair": false, "body_html": "<div class=\"md\"><p>You misspelled &quot;Google maps directions API&quot;</p>\n</div>", "gildings": {}, "collapsed_reason": null, "associated_award": null, "stickied": false, "author_premium": false, "subreddit_type": "public", "can_gild": true, "top_awarded_type": null, "author_flair_text_color": null, "score_hidden": false, "permalink": "/r/wallstreetbets/comments/kdzlvr/wsb_doesnt_touch_garbage_like_that/gg12mxu/", "num_reports": null, "locked": false, "name": "t1_gg12mxu", "created": 1608154944.0, "author_flair_text": null, "treatment_tags": [], "created_utc": 1608126144.0, "subreddit_name_prefixed": "r/wallstreetbets", "controversiality": 0, "depth": 3, "author_flair_background_color": null, "collapsed_because_crowd_control": null, "mod_reports": [], "mod_note": null, "distinguished": null, "replies": []}]}]}, {"total_awards_received": 0, "approved_at_utc": null, "comment_type": null, "awarders": [], "mod_reason_by": null, "banned_by": null, "ups": 13, "author_flair_type": "text", "removal_reason": null, "link_id": "t3_kdzlvr", "author_flair_template_id": null, "likes": null, "user_reports": [], "saved": false, "id": "gfzr7n4", "banned_at_utc": null, "mod_reason_title": null, "gilded": 0, "archived": false, "no_follow": false, "author": {"name": "hongcongchickwonh", "fullname": "t2_4r1rdqso"}, "can_mod_post": false, "send_replies": true, "parent_id": "t1_gfzjqt9", "score": 13, "author_fullname": "t2_4r1rdqso", "report_reasons": null, "approved_by": null, "all_awardings": [], "subreddit_id": "t5_2th52", "collapsed": false, "body": "Hey speak for yourself. I work at Wendy\u2019s!", "edited": false, "author_flair_css_class": null, "is_submitter": false, "downs": 0, "author_flair_richtext": [], "author_patreon_flair": false, "body_html": "<div class=\"md\"><p>Hey speak for yourself. I work at Wendy\u2019s!</p>\n</div>", "gildings": {}, "collapsed_reason": null, "associated_award": null, "stickied": false, "author_premium": false, "subreddit_type": "public", "can_gild": true, "top_awarded_type": null, "author_flair_text_color": null, "score_hidden": false, "permalink": "/r/wallstreetbets/comments/kdzlvr/wsb_doesnt_touch_garbage_like_that/gfzr7n4/", "num_reports": null, "locked": false, "name": "t1_gfzr7n4", "created": 1608116271.0, "author_flair_text": null, "treatment_tags": [], "created_utc": 1608087471.0, "subreddit_name_prefixed": "r/wallstreetbets", "controversiality": 0, "depth": 1, "author_flair_background_color": null, "collapsed_because_crowd_control": null, "mod_reports": [], "mod_note": null, "distinguished": null, "replies": []}]}, {"total_awards_received": 0, "approved_at_utc": null, "comment_type": null, "awarders": [], "mod_reason_by": null, "banned_by": null, "ups": 119, "author_flair_type": "text", "removal_reason": null, "link_id": "t3_kdzlvr", "author_flair_template_id": null, "likes": null, "user_reports": [], "saved": false, "id": "gfzjsji", "banned_at_utc": null, "mod_reason_title": null, "gilded": 0, "archived": false, "no_follow": false, "author": {"name": "Wrektdev", "fullname": "t2_kvb4h"}, "can_mod_post": false, "send_replies": true, "parent_id": "t3_kdzlvr", "score": 119, "author_fullname": "t2_kvb4h", "report_reasons": null, "approved_by": null, "all_awardings": [], "subreddit_id": "t5_2th52", "body": "Get back at me when Roblox moons to Pluto on the 7th day after ipo", "edited": false, "downs": 0, "author_flair_css_class": null, "is_submitter": false, "collapsed": false, "author_flair_richtext": [], "author_patreon_flair": false, "body_html": "<div class=\"md\"><p>Get back at me when Roblox moons to Pluto on the 7th day after ipo</p>\n</div>", "gildings": {}, "collapsed_reason": null, "associated_award": null, "stickied": false, "author_premium": false, "subreddit_type": "public", "can_gild": true, "top_awarded_type": null, "author_flair_text_color": null, "score_hidden": false, "permalink": "/r/wallstreetbets/comments/kdzlvr/wsb_doesnt_touch_garbage_like_that/gfzjsji/", "num_reports": null, "locked": false, "name": "t1_gfzjsji", "created": 1608112125.0, "author_flair_text": null, "treatment_tags": [], "created_utc": 1608083325.0, "subreddit_name_prefixed": "r/wallstreetbets", "controversiality": 0, "depth": 0, "author_flair_background_color": null, "collapsed_because_crowd_control": null, "mod_reports": [], "mod_note": null, "distinguished": null, "replies": [{"total_awards_received": 0, "approved_at_utc": null, "comment_type": null, "awarders": [], "mod_reason_by": null, "banned_by": null, "ups": 70, "author_flair_type": "text", "removal_reason": null, "link_id": "t3_kdzlvr", "author_flair_template_id": null, "likes": null, "user_reports": [], "saved": false, "id": "gfzkety", "banned_at_utc": null, "mod_reason_title": null, "gilded": 0, "archived": false, "no_follow": false, "author": {"name": "Larrysfuneral", "fullname": "t2_1itbstge"}, "can_mod_post": false, "send_replies": true, "parent_id": "t1_gfzjsji", "score": 70, "author_fullname": "t2_1itbstge", "report_reasons": null, "approved_by": null, "all_awardings": [], "subreddit_id": "t5_2th52", "collapsed": false, "body": "I actually believe in this, Roblox is like a casino for smelly kids that steal their parents credit cards for Roblox. I mean how is this not a problem, my nephews spend tons of money opening Eggs in a game called Adopt Me, it\u2019s insane.", "edited": false, "author_flair_css_class": null, "is_submitter": true, "downs": 0, "author_flair_richtext": [], "author_patreon_flair": false, "body_html": "<div class=\"md\"><p>I actually believe in this, Roblox is like a casino for smelly kids that steal their parents credit cards for Roblox. I mean how is this not a problem, my nephews spend tons of money opening Eggs in a game called Adopt Me, it\u2019s insane.</p>\n</div>", "gildings": {}, "collapsed_reason": null, "associated_award": null, "stickied": false, "author_premium": false, "subreddit_type": "public", "can_gild": true, "top_awarded_type": null, "author_flair_text_color": null, "score_hidden": false, "permalink": "/r/wallstreetbets/comments/kdzlvr/wsb_doesnt_touch_garbage_like_that/gfzkety/", "num_reports": null, "locked": false, "name": "t1_gfzkety", "created": 1608112467.0, "author_flair_text": null, "treatment_tags": [], "created_utc": 1608083667.0, "subreddit_name_prefixed": "r/wallstreetbets", "controversiality": 0, "depth": 1, "author_flair_background_color": null, "collapsed_because_crowd_control": null, "mod_reports": [], "mod_note": null, "distinguished": null, "replies": [{"total_awards_received": 0, "approved_at_utc": null, "comment_type": null, "awarders": [], "mod_reason_by": null, "banned_by": null, "ups": 17, "author_flair_type": "text", "removal_reason": null, "link_id": "t3_kdzlvr", "author_flair_template_id": null, "likes": null, "user_reports": [], "saved": false, "id": "gfztchs", "banned_at_utc": null, "mod_reason_title": null, "gilded": 0, "archived": false, "no_follow": false, "author": {"name": "crumbycanadianpoutin", "fullname": "t2_15xah71k"}, "can_mod_post": false, "created_utc": 1608088688.0, "send_replies": true, "parent_id": "t1_gfzkety", "score": 17, "author_fullname": "t2_15xah71k", "report_reasons": null, "approved_by": null, "all_awardings": [], "subreddit_id": "t5_2th52", "body": "You think Citron would go through the trouble of seeking out parents whose kids were targeted by pedos?", "edited": false, "author_flair_css_class": null, "is_submitter": false, "downs": 0, "author_flair_richtext": [], "author_patreon_flair": false, "body_html": "<div class=\"md\"><p>You think Citron would go through the trouble of seeking out parents whose kids were targeted by pedos?</p>\n</div>", "gildings": {}, "collapsed_reason": null, "associated_award": null, "stickied": false, "author_premium": false, "subreddit_type": "public", "can_gild": true, "top_awarded_type": null, "author_flair_text_color": null, "score_hidden": false, "permalink": "/r/wallstreetbets/comments/kdzlvr/wsb_doesnt_touch_garbage_like_that/gfztchs/", "num_reports": null, "locked": false, "name": "t1_gfztchs", "created": 1608117488.0, "author_flair_text": null, "treatment_tags": [], "collapsed": false, "subreddit_name_prefixed": "r/wallstreetbets", "controversiality": 0, "depth": 2, "author_flair_background_color": null, "collapsed_because_crowd_control": null, "mod_reports": [], "mod_note": null, "distinguished": null, "replies": [{"total_awards_received": 0, "approved_at_utc": null, "comment_type": null, "awarders": [], "mod_reason_by": null, "banned_by": null, "ups": 20, "author_flair_type": "richtext", "removal_reason": null, "link_id": "t3_kdzlvr", "author_flair_template_id": null, "likes": null, "user_reports": [], "saved": false, "id": "gfzygn5", "banned_at_utc": null, "mod_reason_title": null, "gilded": 0, "archived": false, "no_follow": false, "author": {"name": "pgh1979", "fullname": "t2_4wj69nbh"}, "can_mod_post": false, "send_replies": true, "parent_id": "t1_gfztchs", "score": 20, "author_fullname": "t2_4wj69nbh", "report_reasons": null, "approved_by": null, "all_awardings": [], "subreddit_id": "t5_2th52", "body": "Why would Citron have to seek out anyone? I thought Citron's analysts moonlighted as analysts - their day job was diddling kids online. Surely they know where their victims live.", "edited": false, "downs": 0, "author_flair_css_class": null, "is_submitter": false, "collapsed": false, "author_flair_richtext": [{"e": "text", "t": "\u001b201123:7:1"}], "author_patreon_flair": false, "body_html": "<div class=\"md\"><p>Why would Citron have to seek out anyone? I thought Citron&#39;s analysts moonlighted as analysts - their day job was diddling kids online. Surely they know where their victims live.</p>\n</div>", "gildings": {}, "collapsed_reason": null, "associated_award": null, "stickied": false, "author_premium": false, "subreddit_type": "public", "can_gild": true, "top_awarded_type": null, "author_flair_text_color": "dark", "score_hidden": false, "permalink": "/r/wallstreetbets/comments/kdzlvr/wsb_doesnt_touch_garbage_like_that/gfzygn5/", "num_reports": null, "locked": false, "name": "t1_gfzygn5", "created": 1608120584.0, "author_flair_text": "\u001b201123:7:1", "treatment_tags": [], "created_utc": 1608091784.0, "subreddit_name_prefixed": "r/wallstreetbets", "controversiality": 0, "depth": 3, "author_flair_background_color": "", "collapsed_because_crowd_control": null, "mod_reports": [], "mod_note": null, "distinguished": null, "replies": [{"total_awards_received": 0, "approved_at_utc": null, "comment_type": null, "awarders": [], "mod_reason_by": null, "banned_by": null, "ups": 15, "author_flair_type": "text", "removal_reason": null, "link_id": "t3_kdzlvr", "author_flair_template_id": null, "likes": null, "user_reports": [], "saved": false, "id": "gfzyoin", "banned_at_utc": null, "mod_reason_title": null, "gilded": 0, "archived": false, "no_follow": false, "author": {"name": "crumbycanadianpoutin", "fullname": "t2_15xah71k"}, "can_mod_post": false, "send_replies": true, "parent_id": "t1_gfzygn5", "score": 15, "author_fullname": "t2_15xah71k", "report_reasons": null, "approved_by": null, "all_awardings": [], "subreddit_id": "t5_2th52", "collapsed": false, "body": "\"You won't believe how easy it was for us to get 10 year old Timmy Thomson from Georgia to send us pictures of his booty hole. Puts on RBLX going to $0\"", "edited": false, "author_flair_css_class": null, "is_submitter": false, "downs": 0, "author_flair_richtext": [], "author_patreon_flair": false, "body_html": "<div class=\"md\"><p>&quot;You won&#39;t believe how easy it was for us to get 10 year old Timmy Thomson from Georgia to send us pictures of his booty hole. Puts on RBLX going to $0&quot;</p>\n</div>", "gildings": {}, "collapsed_reason": null, "associated_award": null, "stickied": false, "author_premium": false, "subreddit_type": "public", "can_gild": true, "top_awarded_type": null, "author_flair_text_color": null, "score_hidden": false, "permalink": "/r/wallstreetbets/comments/kdzlvr/wsb_doesnt_touch_garbage_like_that/gfzyoin/", "num_reports": null, "locked": false, "name": "t1_gfzyoin", "created": 1608120718.0, "author_flair_text": null, "treatment_tags": [], "created_utc": 1608091918.0, "subreddit_name_prefixed": "r/wallstreetbets", "controversiality": 0, "depth": 4, "author_flair_background_color": null, "collapsed_because_crowd_control": null, "mod_reports": [], "mod_note": null, "distinguished": null, "replies": []}]}]}, {"total_awards_received": 0, "approved_at_utc": null, "comment_type": null, "awarders": [], "mod_reason_by": null, "banned_by": null, "ups": 9, "author_flair_type": "text", "removal_reason": null, "link_id": "t3_kdzlvr", "author_flair_template_id": null, "likes": null, "user_reports": [], "saved": false, "id": "gg0iqp7", "banned_at_utc": null, "mod_reason_title": null, "gilded": 0, "archived": false, "no_follow": false, "author": {"name": "naIamgood", "fullname": "t2_84cbn8p"}, "can_mod_post": false, "created_utc": 1608107633.0, "send_replies": true, "parent_id": "t1_gfzkety", "score": 9, "author_fullname": "t2_84cbn8p", "report_reasons": null, "approved_by": null, "all_awardings": [], "subreddit_id": "t5_2th52", "body": "Kids have total addiction to this game, damn has worst graphics than the games I played in the late 1990's", "edited": false, "author_flair_css_class": null, "is_submitter": false, "downs": 0, "author_flair_richtext": [], "author_patreon_flair": false, "body_html": "<div class=\"md\"><p>Kids have total addiction to this game, damn has worst graphics than the games I played in the late 1990&#39;s</p>\n</div>", "gildings": {}, "collapsed_reason": null, "associated_award": null, "stickied": false, "author_premium": false, "subreddit_type": "public", "can_gild": true, "top_awarded_type": null, "author_flair_text_color": null, "score_hidden": false, "permalink": "/r/wallstreetbets/comments/kdzlvr/wsb_doesnt_touch_garbage_like_that/gg0iqp7/", "num_reports": null, "locked": false, "name": "t1_gg0iqp7", "created": 1608136433.0, "author_flair_text": null, "treatment_tags": [], "collapsed": false, "subreddit_name_prefixed": "r/wallstreetbets", "controversiality": 0, "depth": 2, "author_flair_background_color": null, "collapsed_because_crowd_control": null, "mod_reports": [], "mod_note": null, "distinguished": null, "replies": []}]}, {"total_awards_received": 0, "approved_at_utc": null, "comment_type": null, "awarders": [], "mod_reason_by": null, "banned_by": null, "ups": 9, "author_flair_type": "text", "removal_reason": null, "link_id": "t3_kdzlvr", "author_flair_template_id": null, "likes": null, "user_reports": [], "saved": false, "id": "gg071nn", "banned_at_utc": null, "mod_reason_title": null, "gilded": 0, "archived": false, "no_follow": false, "author": {"name": "ilikevenndiagrams", "fullname": "t2_8v3e6lfm"}, "can_mod_post": false, "send_replies": true, "parent_id": "t1_gfzjsji", "score": 9, "author_fullname": "t2_8v3e6lfm", "report_reasons": null, "approved_by": null, "all_awardings": [], "subreddit_id": "t5_2th52", "collapsed": false, "body": "dd: saw a guy here give his 7 year old 100 robux", "edited": false, "author_flair_css_class": null, "is_submitter": false, "downs": 0, "author_flair_richtext": [], "author_patreon_flair": false, "body_html": "<div class=\"md\"><p>dd: saw a guy here give his 7 year old 100 robux</p>\n</div>", "gildings": {}, "collapsed_reason": null, "associated_award": null, "stickied": false, "author_premium": true, "subreddit_type": "public", "can_gild": true, "top_awarded_type": null, "author_flair_text_color": null, "score_hidden": false, "permalink": "/r/wallstreetbets/comments/kdzlvr/wsb_doesnt_touch_garbage_like_that/gg071nn/", "num_reports": null, "locked": false, "name": "t1_gg071nn", "created": 1608126411.0, "author_flair_text": null, "treatment_tags": [], "created_utc": 1608097611.0, "subreddit_name_prefixed": "r/wallstreetbets", "controversiality": 0, "depth": 1, "author_flair_background_color": null, "collapsed_because_crowd_control": null, "mod_reports": [], "mod_note": null, "distinguished": null, "replies": [{"total_awards_received": 0, "approved_at_utc": null, "comment_type": null, "awarders": [], "mod_reason_by": null, "banned_by": null, "ups": 1, "author_flair_type": "text", "removal_reason": null, "link_id": "t3_kdzlvr", "author_flair_template_id": null, "likes": null, "user_reports": [], "saved": false, "id": "gg1w4l3", "banned_at_utc": null, "mod_reason_title": null, "gilded": 0, "archived": false, "no_follow": true, "author": {"name": "50calhipfire", "fullname": "t2_8p5z9mj7"}, "can_mod_post": false, "created_utc": 1608141485.0, "send_replies": true, "parent_id": "t1_gg071nn", "score": 1, "author_fullname": "t2_8p5z9mj7", "report_reasons": null, "approved_by": null, "all_awardings": [], "subreddit_id": "t5_2th52", "body": "$100 for robux, 100 robux won't get you much on there. Not that I'd know or anything", "edited": false, "author_flair_css_class": null, "is_submitter": false, "downs": 0, "author_flair_richtext": [], "author_patreon_flair": false, "body_html": "<div class=\"md\"><p>$100 for robux, 100 robux won&#39;t get you much on there. Not that I&#39;d know or anything</p>\n</div>", "gildings": {}, "collapsed_reason": null, "associated_award": null, "stickied": false, "author_premium": false, "subreddit_type": "public", "can_gild": true, "top_awarded_type": null, "author_flair_text_color": null, "score_hidden": false, "permalink": "/r/wallstreetbets/comments/kdzlvr/wsb_doesnt_touch_garbage_like_that/gg1w4l3/", "num_reports": null, "locked": false, "name": "t1_gg1w4l3", "created": 1608170285.0, "author_flair_text": null, "treatment_tags": [], "collapsed": false, "subreddit_name_prefixed": "r/wallstreetbets", "controversiality": 0, "depth": 2, "author_flair_background_color": null, "collapsed_because_crowd_control": null, "mod_reports": [], "mod_note": null, "distinguished": null, "replies": []}]}, {"total_awards_received": 0, "approved_at_utc": null, "comment_type": null, "awarders": [], "mod_reason_by": null, "banned_by": null, "ups": 5, "author_flair_type": "text", "removal_reason": null, "link_id": "t3_kdzlvr", "author_flair_template_id": null, "likes": null, "user_reports": [], "saved": false, "id": "gg0mm4e", "banned_at_utc": null, "mod_reason_title": null, "gilded": 0, "archived": false, "no_follow": false, "author": {"name": "ajax5206", "fullname": "t2_2apmgp"}, "can_mod_post": false, "send_replies": true, "parent_id": "t1_gfzjsji", "score": 5, "author_fullname": "t2_2apmgp", "report_reasons": null, "approved_by": null, "all_awardings": [], "subreddit_id": "t5_2th52", "collapsed": false, "body": "They delayed the ipo reee", "edited": false, "author_flair_css_class": null, "is_submitter": false, "downs": 0, "author_flair_richtext": [], "author_patreon_flair": false, "body_html": "<div class=\"md\"><p>They delayed the ipo reee</p>\n</div>", "gildings": {}, "collapsed_reason": null, "associated_award": null, "stickied": false, "author_premium": false, "subreddit_type": "public", "can_gild": true, "top_awarded_type": null, "author_flair_text_color": null, "score_hidden": false, "permalink": "/r/wallstreetbets/comments/kdzlvr/wsb_doesnt_touch_garbage_like_that/gg0mm4e/", "num_reports": null, "locked": false, "name": "t1_gg0mm4e", "created": 1608140205.0, "author_flair_text": null, "treatment_tags": [], "created_utc": 1608111405.0, "subreddit_name_prefixed": "r/wallstreetbets", "controversiality": 0, "depth": 1, "author_flair_background_color": null, "collapsed_because_crowd_control": null, "mod_reports": [], "mod_note": null, "distinguished": null, "replies": []}, {"total_awards_received": 0, "approved_at_utc": null, "comment_type": null, "awarders": [], "mod_reason_by": null, "banned_by": null, "ups": 3, "author_flair_type": "text", "removal_reason": null, "link_id": "t3_kdzlvr", "author_flair_template_id": null, "likes": null, "user_reports": [], "saved": false, "id": "gg13nh3", "banned_at_utc": null, "mod_reason_title": null, "gilded": 0, "archived": false, "no_follow": false, "author": {"name": "aiuslocutius", "fullname": "t2_103cry"}, "can_mod_post": false, "send_replies": true, "parent_id": "t1_gfzjsji", "score": 3, "author_fullname": "t2_103cry", "report_reasons": null, "approved_by": null, "all_awardings": [], "subreddit_id": "t5_2th52", "collapsed": false, "body": "If they again pull the same crap they did with airbnb l, never gonna touch an IPO again. They inflate the price to x2s and expect us to pay them that premium just to be part of the hype. No.", "edited": false, "author_flair_css_class": null, "is_submitter": false, "downs": 0, "author_flair_richtext": [], "author_patreon_flair": false, "body_html": "<div class=\"md\"><p>If they again pull the same crap they did with airbnb l, never gonna touch an IPO again. They inflate the price to x2s and expect us to pay them that premium just to be part of the hype. No.</p>\n</div>", "gildings": {}, "collapsed_reason": null, "associated_award": null, "stickied": false, "author_premium": false, "subreddit_type": "public", "can_gild": true, "top_awarded_type": null, "author_flair_text_color": null, "score_hidden": false, "permalink": "/r/wallstreetbets/comments/kdzlvr/wsb_doesnt_touch_garbage_like_that/gg13nh3/", "num_reports": null, "locked": false, "name": "t1_gg13nh3", "created": 1608155599.0, "author_flair_text": null, "treatment_tags": [], "created_utc": 1608126799.0, "subreddit_name_prefixed": "r/wallstreetbets", "controversiality": 0, "depth": 1, "author_flair_background_color": null, "collapsed_because_crowd_control": null, "mod_reports": [], "mod_note": null, "distinguished": null, "replies": []}]}, {"total_awards_received": 0, "approved_at_utc": null, "comment_type": null, "awarders": [], "mod_reason_by": null, "banned_by": null, "ups": 58, "author_flair_type": "text", "removal_reason": null, "link_id": "t3_kdzlvr", "author_flair_template_id": null, "likes": null, "user_reports": [], "saved": false, "id": "gfzjpr9", "banned_at_utc": null, "mod_reason_title": null, "gilded": 0, "archived": false, "no_follow": false, "author": {"name": "kimsksk", "fullname": "t2_1a8pdx5s"}, "can_mod_post": false, "send_replies": true, "parent_id": "t3_kdzlvr", "score": 58, "author_fullname": "t2_1a8pdx5s", "report_reasons": null, "approved_by": null, "all_awardings": [], "subreddit_id": "t5_2th52", "body": "We're gonna have to fuck these guys up for talking shit behind our backs.", "edited": false, "downs": 0, "author_flair_css_class": null, "is_submitter": false, "collapsed": false, "author_flair_richtext": [], "author_patreon_flair": false, "body_html": "<div class=\"md\"><p>We&#39;re gonna have to fuck these guys up for talking shit behind our backs.</p>\n</div>", "gildings": {}, "collapsed_reason": null, "associated_award": null, "stickied": false, "author_premium": false, "subreddit_type": "public", "can_gild": true, "top_awarded_type": null, "author_flair_text_color": "", "score_hidden": false, "permalink": "/r/wallstreetbets/comments/kdzlvr/wsb_doesnt_touch_garbage_like_that/gfzjpr9/", "num_reports": null, "locked": false, "name": "t1_gfzjpr9", "created": 1608112082.0, "author_flair_text": "", "treatment_tags": [], "created_utc": 1608083282.0, "subreddit_name_prefixed": "r/wallstreetbets", "controversiality": 0, "depth": 0, "author_flair_background_color": "", "collapsed_because_crowd_control": null, "mod_reports": [], "mod_note": null, "distinguished": null, "replies": [{"total_awards_received": 0, "approved_at_utc": null, "comment_type": null, "awarders": [], "mod_reason_by": null, "banned_by": null, "ups": 46, "author_flair_type": "text", "removal_reason": null, "link_id": "t3_kdzlvr", "author_flair_template_id": null, "likes": null, "user_reports": [], "saved": false, "id": "gfzklk7", "banned_at_utc": null, "mod_reason_title": null, "gilded": 0, "archived": false, "no_follow": false, "author": {"name": "Larrysfuneral", "fullname": "t2_1itbstge"}, "can_mod_post": false, "send_replies": true, "parent_id": "t1_gfzjpr9", "score": 46, "author_fullname": "t2_1itbstge", "report_reasons": null, "approved_by": null, "all_awardings": [], "subreddit_id": "t5_2th52", "collapsed": false, "body": "Don\u2019t worry, we\u2019ll make these boomers suffer by clicking random stocks and making our money machine print without reason.", "edited": false, "author_flair_css_class": null, "is_submitter": true, "downs": 0, "author_flair_richtext": [], "author_patreon_flair": false, "body_html": "<div class=\"md\"><p>Don\u2019t worry, we\u2019ll make these boomers suffer by clicking random stocks and making our money machine print without reason.</p>\n</div>", "gildings": {}, "collapsed_reason": null, "associated_award": null, "stickied": false, "author_premium": false, "subreddit_type": "public", "can_gild": true, "top_awarded_type": null, "author_flair_text_color": null, "score_hidden": false, "permalink": "/r/wallstreetbets/comments/kdzlvr/wsb_doesnt_touch_garbage_like_that/gfzklk7/", "num_reports": null, "locked": false, "name": "t1_gfzklk7", "created": 1608112569.0, "author_flair_text": null, "treatment_tags": [], "created_utc": 1608083769.0, "subreddit_name_prefixed": "r/wallstreetbets", "controversiality": 0, "depth": 1, "author_flair_background_color": null, "collapsed_because_crowd_control": null, "mod_reports": [], "mod_note": null, "distinguished": null, "replies": [{"total_awards_received": 0, "approved_at_utc": null, "comment_type": null, "awarders": [], "mod_reason_by": null, "banned_by": null, "ups": 12, "author_flair_type": "richtext", "removal_reason": null, "link_id": "t3_kdzlvr", "author_flair_template_id": null, "likes": null, "user_reports": [], "saved": false, "id": "gfzqrq3", "banned_at_utc": null, "mod_reason_title": null, "gilded": 0, "archived": false, "no_follow": false, "author": {"name": "TheDude_Abides_Man", "fullname": "t2_2qqoxj8z"}, "can_mod_post": false, "created_utc": 1608087226.0, "send_replies": true, "parent_id": "t1_gfzklk7", "score": 12, "author_fullname": "t2_2qqoxj8z", "report_reasons": null, "approved_by": null, "all_awardings": [], "subreddit_id": "t5_2th52", "body": "Goes BBRRRRRRRR \ud83d\udcb5\ud83d\udcb5\ud83d\udcb5", "edited": false, "author_flair_css_class": null, "is_submitter": false, "downs": 0, "author_flair_richtext": [{"e": "text", "t": "\u001b201209:1:1"}], "author_patreon_flair": false, "body_html": "<div class=\"md\"><p>Goes BBRRRRRRRR \ud83d\udcb5\ud83d\udcb5\ud83d\udcb5</p>\n</div>", "gildings": {}, "collapsed_reason": null, "associated_award": null, "stickied": false, "author_premium": false, "subreddit_type": "public", "can_gild": true, "top_awarded_type": null, "author_flair_text_color": "dark", "score_hidden": false, "permalink": "/r/wallstreetbets/comments/kdzlvr/wsb_doesnt_touch_garbage_like_that/gfzqrq3/", "num_reports": null, "locked": false, "name": "t1_gfzqrq3", "created": 1608116026.0, "author_flair_text": "\u001b201209:1:1", "treatment_tags": [], "collapsed": false, "subreddit_name_prefixed": "r/wallstreetbets", "controversiality": 0, "depth": 2, "author_flair_background_color": "", "collapsed_because_crowd_control": null, "mod_reports": [], "mod_note": null, "distinguished": null, "replies": [{"total_awards_received": 0, "approved_at_utc": null, "comment_type": null, "awarders": [], "mod_reason_by": null, "banned_by": null, "ups": 7, "author_flair_type": "text", "removal_reason": null, "link_id": "t3_kdzlvr", "author_flair_template_id": null, "likes": null, "user_reports": [], "saved": false, "id": "gfzr137", "banned_at_utc": null, "mod_reason_title": null, "gilded": 0, "archived": false, "no_follow": false, "author": {"name": "Larrysfuneral", "fullname": "t2_1itbstge"}, "can_mod_post": false, "send_replies": true, "parent_id": "t1_gfzqrq3", "score": 7, "author_fullname": "t2_1itbstge", "report_reasons": null, "approved_by": null, "all_awardings": [], "subreddit_id": "t5_2th52", "body": "[Ca$h Machine](https://youtu.be/9rx0eqQl8wk)", "edited": false, "downs": 0, "author_flair_css_class": null, "is_submitter": true, "collapsed": false, "author_flair_richtext": [], "author_patreon_flair": false, "body_html": "<div class=\"md\"><p><a href=\"https://youtu.be/9rx0eqQl8wk\">Ca$h Machine</a></p>\n</div>", "gildings": {}, "collapsed_reason": null, "associated_award": null, "stickied": false, "author_premium": false, "subreddit_type": "public", "can_gild": true, "top_awarded_type": null, "author_flair_text_color": null, "score_hidden": false, "permalink": "/r/wallstreetbets/comments/kdzlvr/wsb_doesnt_touch_garbage_like_that/gfzr137/", "num_reports": null, "locked": false, "name": "t1_gfzr137", "created": 1608116171.0, "author_flair_text": null, "treatment_tags": [], "created_utc": 1608087371.0, "subreddit_name_prefixed": "r/wallstreetbets", "controversiality": 0, "depth": 3, "author_flair_background_color": null, "collapsed_because_crowd_control": null, "mod_reports": [], "mod_note": null, "distinguished": null, "replies": []}]}]}]}]}