{"approved_at_utc": null, "selftext": "", "author_fullname": "t2_agaw8i9", "saved": false, "mod_reason_title": null, "gilded": 0, "clicked": false, "title": "My first YOLO, what do you guys think?", "link_flair_richtext": [{"e": "text", "t": "YOLO"}], "subreddit_name_prefixed": "r/wallstreetbets", "hidden": false, "pwls": 7, "link_flair_css_class": "yolo", "downs": 0, "thumbnail_height": 106, "top_awarded_type": null, "hide_score": true, "name": "t3_kjfpf3", "quarantine": false, "link_flair_text_color": "light", "upvote_ratio": 0.86, "author_flair_background_color": null, "subreddit_type": "public", "ups": 10, "total_awards_received": 0, "media_embed": {}, "thumbnail_width": 140, "author_flair_template_id": null, "is_original_content": false, "user_reports": [], "secure_media": null, "is_reddit_media_domain": true, "is_meta": false, "category": null, "secure_media_embed": {}, "link_flair_text": "YOLO", "can_mod_post": false, "score": 10, "approved_by": null, "author_premium": false, "thumbnail": "https://b.thumbs.redditmedia.com/NnBuEjDrWjcBrm8R7g59kiTCxt5FDvEvJFjBMpXR23Q.jpg", "edited": false, "author_flair_css_class": null, "author_flair_richtext": [], "gildings": {}, "post_hint": "image", "content_categories": null, "is_self": false, "mod_note": null, "created": 1608846464.0, "link_flair_type": "richtext", "wls": 7, "removed_by_category": null, "banned_by": null, "author_flair_type": "text", "domain": "i.redd.it", "allow_live_comments": false, "selftext_html": null, "likes": null, "suggested_sort": "confidence", "banned_at_utc": null, "url_overridden_by_dest": "https://i.redd.it/mpi0u67e35761.jpg", "view_count": null, "archived": false, "no_follow": false, "is_crosspostable": false, "pinned": false, "over_18": false, "preview": {"images": [{"source": {"url": "https://preview.redd.it/mpi0u67e35761.jpg?auto=webp&s=9e12e3523c21894d2762953f44209a6a386bb89a", "width": 1125, "height": 853}, "resolutions": [{"url": "https://preview.redd.it/mpi0u67e35761.jpg?width=108&crop=smart&auto=webp&s=81c4aae592cd8746c9c2ff86a26737104a6b2fb8", "width": 108, "height": 81}, {"url": "https://preview.redd.it/mpi0u67e35761.jpg?width=216&crop=smart&auto=webp&s=2e088ef5519c06416faaf9e02c19a34c6b54db3b", "width": 216, "height": 163}, {"url": "https://preview.redd.it/mpi0u67e35761.jpg?width=320&crop=smart&auto=webp&s=89db9286be6f8132e891cd4143c6a03262fc5987", "width": 320, "height": 242}, {"url": "https://preview.redd.it/mpi0u67e35761.jpg?width=640&crop=smart&auto=webp&s=98b991ecc282520a66d67d61bfb1194dbe6af8de", "width": 640, "height": 485}, {"url": "https://preview.redd.it/mpi0u67e35761.jpg?width=960&crop=smart&auto=webp&s=12dbfeb2b68cac96089d30916ec2828812718dbd", "width": 960, "height": 727}, {"url": "https://preview.redd.it/mpi0u67e35761.jpg?width=1080&crop=smart&auto=webp&s=ed7368452075a056e09de1fe3e9b32951c073033", "width": 1080, "height": 818}], "variants": {}, "id": "oqPNTOF9bhlGy4uVUuxzWTQMMw1VHkXwyEVxK9bjC0o"}], "enabled": true}, "all_awardings": [], "awarders": [], "media_only": false, "link_flair_template_id": "da18a43a-83c5-11e8-9b6c-0e287561ddb8", "can_gild": false, "spoiler": false, "locked": false, "author_flair_text": null, "treatment_tags": [], "visited": false, "removed_by": null, "num_reports": null, "distinguished": null, "subreddit_id": "t5_2th52", "mod_reason_by": null, "removal_reason": null, "link_flair_background_color": "#0392cf", "id": "kjfpf3", "is_robot_indexable": true, "report_reasons": null, "author": {"name": "oxle504", "fullname": "t2_agaw8i9"}, "discussion_type": null, "num_comments": 19, "send_replies": true, "whitelist_status": "some_ads", "contest_mode": false, "mod_reports": [], "author_patreon_flair": false, "author_flair_text_color": null, "permalink": "/r/wallstreetbets/comments/kjfpf3/my_first_yolo_what_do_you_guys_think/", "parent_whitelist_status": "some_ads", "stickied": false, "url": "https://i.redd.it/mpi0u67e35761.jpg", "subreddit_subscribers": 1738757, "created_utc": 1608817664.0, "num_crossposts": 0, "media": null, "is_video": false, "comment_limit": 2048, "comment_sort": "confidence", "comments": [{"total_awards_received": 0, "approved_at_utc": null, "comment_type": null, "awarders": [], "mod_reason_by": null, "banned_by": null, "ups": 14, "author_flair_type": "richtext", "removal_reason": null, "link_id": "t3_kjfpf3", "author_flair_template_id": null, "likes": null, "user_reports": [], "saved": false, "id": "ggwc485", "banned_at_utc": null, "mod_reason_title": null, "gilded": 0, "archived": false, "no_follow": false, "author": {"name": "sillyhands1", "fullname": "t2_1pyssmoc"}, "can_mod_post": false, "send_replies": true, "parent_id": "t3_kjfpf3", "score": 14, "author_fullname": "t2_1pyssmoc", "report_reasons": null, "approved_by": null, "all_awardings": [], "subreddit_id": "t5_2th52", "body": "Theta gods are gonna eat all your tendies.", "edited": false, "downs": 0, "author_flair_css_class": null, "is_submitter": false, "collapsed": false, "author_flair_richtext": [{"e": "text", "t": "\u001b201202:7:1"}], "author_patreon_flair": false, "body_html": "<div class=\"md\"><p>Theta gods are gonna eat all your tendies.</p>\n</div>", "gildings": {}, "collapsed_reason": null, "associated_award": null, "stickied": false, "author_premium": false, "subreddit_type": "public", "can_gild": true, "top_awarded_type": null, "author_flair_text_color": "dark", "score_hidden": false, "permalink": "/r/wallstreetbets/comments/kjfpf3/my_first_yolo_what_do_you_guys_think/ggwc485/", "num_reports": null, "locked": false, "name": "t1_ggwc485", "created": 1608846699.0, "author_flair_text": "\u001b201202:7:1", "treatment_tags": [], "created_utc": 1608817899.0, "subreddit_name_prefixed": "r/wallstreetbets", "controversiality": 0, "depth": 0, "author_flair_background_color": "", "collapsed_because_crowd_control": null, "mod_reports": [], "mod_note": null, "distinguished": null, "replies": [{"total_awards_received": 0, "approved_at_utc": null, "comment_type": null, "awarders": [], "mod_reason_by": null, "banned_by": null, "ups": 3, "author_flair_type": "text", "removal_reason": null, "link_id": "t3_kjfpf3", "author_flair_template_id": null, "likes": null, "user_reports": [], "saved": false, "id": "ggwc78b", "banned_at_utc": null, "mod_reason_title": null, "gilded": 0, "archived": false, "no_follow": true, "author": {"name": "oxle504", "fullname": "t2_agaw8i9"}, "can_mod_post": false, "send_replies": true, "parent_id": "t1_ggwc485", "score": 3, "author_fullname": "t2_agaw8i9", "report_reasons": null, "approved_by": null, "all_awardings": [], "subreddit_id": "t5_2th52", "collapsed": false, "body": "Lmao I\u2019m fucked", "edited": false, "author_flair_css_class": null, "is_submitter": true, "downs": 0, "author_flair_richtext": [], "author_patreon_flair": false, "body_html": "<div class=\"md\"><p>Lmao I\u2019m fucked</p>\n</div>", "gildings": {}, "collapsed_reason": null, "associated_award": null, "stickied": false, "author_premium": false, "subreddit_type": "public", "can_gild": true, "top_awarded_type": null, "author_flair_text_color": null, "score_hidden": false, "permalink": "/r/wallstreetbets/comments/kjfpf3/my_first_yolo_what_do_you_guys_think/ggwc78b/", "num_reports": null, "locked": false, "name": "t1_ggwc78b", "created": 1608846764.0, "author_flair_text": null, "treatment_tags": [], "created_utc": 1608817964.0, "subreddit_name_prefixed": "r/wallstreetbets", "controversiality": 0, "depth": 1, "author_flair_background_color": null, "collapsed_because_crowd_control": null, "mod_reports": [], "mod_note": null, "distinguished": null, "replies": [{"total_awards_received": 0, "approved_at_utc": null, "comment_type": null, "awarders": [], "mod_reason_by": null, "banned_by": null, "ups": 7, "author_flair_type": "richtext", "removal_reason": null, "link_id": "t3_kjfpf3", "author_flair_template_id": null, "likes": null, "user_reports": [], "saved": false, "id": "ggwcjgk", "banned_at_utc": null, "mod_reason_title": null, "gilded": 0, "archived": false, "no_follow": false, "author": {"name": "sillyhands1", "fullname": "t2_1pyssmoc"}, "can_mod_post": false, "created_utc": 1608818223.0, "send_replies": true, "parent_id": "t1_ggwc78b", "score": 7, "author_fullname": "t2_1pyssmoc", "report_reasons": null, "approved_by": null, "all_awardings": [], "subreddit_id": "t5_2th52", "body": "Really should\u2019ve dated them longer to avoid theta decay which is huge in the last 30 days. These may print  but i don\u2019t see a big run up before end of January. IV will also fuck you. 2.00 in premium for that option is waayyyyy too high. Good luck though.", "edited": false, "author_flair_css_class": null, "is_submitter": false, "downs": 0, "author_flair_richtext": [{"e": "text", "t": "\u001b201202:7:1"}], "author_patreon_flair": false, "body_html": "<div class=\"md\"><p>Really should\u2019ve dated them longer to avoid theta decay which is huge in the last 30 days. These may print  but i don\u2019t see a big run up before end of January. IV will also fuck you. 2.00 in premium for that option is waayyyyy too high. Good luck though.</p>\n</div>", "gildings": {}, "collapsed_reason": null, "associated_award": null, "stickied": false, "author_premium": false, "subreddit_type": "public", "can_gild": true, "top_awarded_type": null, "author_flair_text_color": "dark", "score_hidden": false, "permalink": "/r/wallstreetbets/comments/kjfpf3/my_first_yolo_what_do_you_guys_think/ggwcjgk/", "num_reports": null, "locked": false, "name": "t1_ggwcjgk", "created": 1608847023.0, "author_flair_text": "\u001b201202:7:1", "treatment_tags": [], "collapsed": false, "subreddit_name_prefixed": "r/wallstreetbets", "controversiality": 0, "depth": 2, "author_flair_background_color": "", "collapsed_because_crowd_control": null, "mod_reports": [], "mod_note": null, "distinguished": null, "replies": [{"total_awards_received": 0, "approved_at_utc": null, "comment_type": null, "awarders": [], "mod_reason_by": null, "banned_by": null, "ups": 2, "author_flair_type": "text", "removal_reason": null, "link_id": "t3_kjfpf3", "author_flair_template_id": null, "likes": null, "user_reports": [], "saved": false, "id": "ggwd9b4", "banned_at_utc": null, "mod_reason_title": null, "gilded": 0, "archived": false, "no_follow": true, "author": {"name": "oxle504", "fullname": "t2_agaw8i9"}, "can_mod_post": false, "send_replies": true, "parent_id": "t1_ggwcjgk", "score": 2, "author_fullname": "t2_agaw8i9", "report_reasons": null, "approved_by": null, "all_awardings": [], "subreddit_id": "t5_2th52", "body": "I\u2019m starting to see that, the decay is real and something not to mess with", "edited": false, "downs": 0, "author_flair_css_class": null, "is_submitter": true, "collapsed": false, "author_flair_richtext": [], "author_patreon_flair": false, "body_html": "<div class=\"md\"><p>I\u2019m starting to see that, the decay is real and something not to mess with</p>\n</div>", "gildings": {}, "collapsed_reason": null, "associated_award": null, "stickied": false, "author_premium": false, "subreddit_type": "public", "can_gild": true, "top_awarded_type": null, "author_flair_text_color": null, "score_hidden": false, "permalink": "/r/wallstreetbets/comments/kjfpf3/my_first_yolo_what_do_you_guys_think/ggwd9b4/", "num_reports": null, "locked": false, "name": "t1_ggwd9b4", "created": 1608847561.0, "author_flair_text": null, "treatment_tags": [], "created_utc": 1608818761.0, "subreddit_name_prefixed": "r/wallstreetbets", "controversiality": 0, "depth": 3, "author_flair_background_color": null, "collapsed_because_crowd_control": null, "mod_reports": [], "mod_note": null, "distinguished": null, "replies": []}, {"total_awards_received": 0, "approved_at_utc": null, "comment_type": null, "awarders": [], "mod_reason_by": null, "banned_by": null, "ups": 2, "author_flair_type": "text", "removal_reason": null, "link_id": "t3_kjfpf3", "author_flair_template_id": null, "likes": null, "user_reports": [], "saved": false, "id": "ggwdlkb", "banned_at_utc": null, "mod_reason_title": null, "gilded": 0, "archived": false, "no_follow": true, "author": {"name": "santcg7", "fullname": "t2_4f4gj0gi"}, "can_mod_post": false, "send_replies": true, "parent_id": "t1_ggwcjgk", "score": 2, "author_fullname": "t2_4f4gj0gi", "report_reasons": null, "approved_by": null, "all_awardings": [], "subreddit_id": "t5_2th52", "body": "Can you please tell me how do you decide if the premium is high or not?", "edited": false, "downs": 0, "author_flair_css_class": null, "is_submitter": false, "collapsed": false, "author_flair_richtext": [], "author_patreon_flair": false, "body_html": "<div class=\"md\"><p>Can you please tell me how do you decide if the premium is high or not?</p>\n</div>", "gildings": {}, "collapsed_reason": null, "associated_award": null, "stickied": false, "author_premium": true, "subreddit_type": "public", "can_gild": true, "top_awarded_type": null, "author_flair_text_color": null, "score_hidden": false, "permalink": "/r/wallstreetbets/comments/kjfpf3/my_first_yolo_what_do_you_guys_think/ggwdlkb/", "num_reports": null, "locked": false, "name": "t1_ggwdlkb", "created": 1608847813.0, "author_flair_text": null, "treatment_tags": [], "created_utc": 1608819013.0, "subreddit_name_prefixed": "r/wallstreetbets", "controversiality": 0, "depth": 3, "author_flair_background_color": null, "collapsed_because_crowd_control": null, "mod_reports": [], "mod_note": null, "distinguished": null, "replies": [{"total_awards_received": 1, "approved_at_utc": null, "comment_type": null, "awarders": [], "mod_reason_by": null, "banned_by": null, "ups": 3, "author_flair_type": "richtext", "removal_reason": null, "link_id": "t3_kjfpf3", "author_flair_template_id": null, "likes": null, "user_reports": [], "saved": false, "id": "ggwe79m", "banned_at_utc": null, "mod_reason_title": null, "gilded": 0, "archived": false, "no_follow": true, "author": {"name": "sillyhands1", "fullname": "t2_1pyssmoc"}, "can_mod_post": false, "send_replies": true, "parent_id": "t1_ggwdlkb", "score": 3, "author_fullname": "t2_1pyssmoc", "report_reasons": null, "approved_by": null, "all_awardings": [{"giver_coin_reward": null, "subreddit_id": null, "is_new": false, "days_of_drip_extension": 0, "coin_price": 125, "id": "award_5f123e3d-4f48-42f4-9c11-e98b566d5897", "penny_donate": null, "coin_reward": 0, "icon_url": "https://i.redd.it/award_images/t5_22cerq/5izbv4fn0md41_Wholesome.png", "days_of_premium": 0, "icon_height": 2048, "tiers_by_required_awardings": null, "resized_icons": [{"url": "https://preview.redd.it/award_images/t5_22cerq/5izbv4fn0md41_Wholesome.png?width=16&height=16&auto=webp&s=92932f465d58e4c16b12b6eac4ca07d27e3d11c0", "width": 16, "height": 16}, {"url": "https://preview.redd.it/award_images/t5_22cerq/5izbv4fn0md41_Wholesome.png?width=32&height=32&auto=webp&s=d11484a208d68a318bf9d4fcf371171a1cb6a7ef", "width": 32, "height": 32}, {"url": "https://preview.redd.it/award_images/t5_22cerq/5izbv4fn0md41_Wholesome.png?width=48&height=48&auto=webp&s=febdf28b6f39f7da7eb1365325b85e0bb49a9f63", "width": 48, "height": 48}, {"url": "https://preview.redd.it/award_images/t5_22cerq/5izbv4fn0md41_Wholesome.png?width=64&height=64&auto=webp&s=b4406a2d88bf86fa3dc8a45aacf7e0c7bdccc4fb", "width": 64, "height": 64}, {"url": "https://preview.redd.it/award_images/t5_22cerq/5izbv4fn0md41_Wholesome.png?width=128&height=128&auto=webp&s=19555b13e3e196b62eeb9160d1ac1d1b372dcb0b", "width": 128, "height": 128}], "icon_width": 2048, "static_icon_width": 2048, "start_date": null, "is_enabled": true, "awardings_required_to_grant_benefits": null, "description": "When you come across a feel-good thing.", "end_date": null, "subreddit_coin_reward": 0, "count": 1, "static_icon_height": 2048, "name": "Wholesome", "resized_static_icons": [{"url": "https://preview.redd.it/award_images/t5_22cerq/5izbv4fn0md41_Wholesome.png?width=16&height=16&auto=webp&s=92932f465d58e4c16b12b6eac4ca07d27e3d11c0", "width": 16, "height": 16}, {"url": "https://preview.redd.it/award_images/t5_22cerq/5izbv4fn0md41_Wholesome.png?width=32&height=32&auto=webp&s=d11484a208d68a318bf9d4fcf371171a1cb6a7ef", "width": 32, "height": 32}, {"url": "https://preview.redd.it/award_images/t5_22cerq/5izbv4fn0md41_Wholesome.png?width=48&height=48&auto=webp&s=febdf28b6f39f7da7eb1365325b85e0bb49a9f63", "width": 48, "height": 48}, {"url": "https://preview.redd.it/award_images/t5_22cerq/5izbv4fn0md41_Wholesome.png?width=64&height=64&auto=webp&s=b4406a2d88bf86fa3dc8a45aacf7e0c7bdccc4fb", "width": 64, "height": 64}, {"url": "https://preview.redd.it/award_images/t5_22cerq/5izbv4fn0md41_Wholesome.png?width=128&height=128&auto=webp&s=19555b13e3e196b62eeb9160d1ac1d1b372dcb0b", "width": 128, "height": 128}], "icon_format": null, "award_sub_type": "GLOBAL", "penny_price": null, "award_type": "global", "static_icon_url": "https://i.redd.it/award_images/t5_22cerq/5izbv4fn0md41_Wholesome.png"}], "subreddit_id": "t5_2th52", "collapsed": false, "body": "Simply looking at the IV really. Anything above 100% is too high in my opinion, but I will sell options in that case. Google the Greeks to understand options before you start buying. Also learn about intrinsic value and time value. Investopedia has all this information", "edited": false, "author_flair_css_class": null, "is_submitter": false, "downs": 0, "author_flair_richtext": [{"e": "text", "t": "\u001b201202:7:1"}], "author_patreon_flair": false, "body_html": "<div class=\"md\"><p>Simply looking at the IV really. Anything above 100% is too high in my opinion, but I will sell options in that case. Google the Greeks to understand options before you start buying. Also learn about intrinsic value and time value. Investopedia has all this information</p>\n</div>", "gildings": {}, "collapsed_reason": null, "associated_award": null, "stickied": false, "author_premium": false, "subreddit_type": "public", "can_gild": true, "top_awarded_type": null, "author_flair_text_color": "dark", "score_hidden": false, "permalink": "/r/wallstreetbets/comments/kjfpf3/my_first_yolo_what_do_you_guys_think/ggwe79m/", "num_reports": null, "locked": false, "name": "t1_ggwe79m", "created": 1608848248.0, "author_flair_text": "\u001b201202:7:1", "treatment_tags": [], "created_utc": 1608819448.0, "subreddit_name_prefixed": "r/wallstreetbets", "controversiality": 0, "depth": 4, "author_flair_background_color": "", "collapsed_because_crowd_control": null, "mod_reports": [], "mod_note": null, "distinguished": null, "replies": [{"total_awards_received": 0, "approved_at_utc": null, "comment_type": null, "awarders": [], "mod_reason_by": null, "banned_by": null, "ups": 1, "author_flair_type": "text", "removal_reason": null, "link_id": "t3_kjfpf3", "author_flair_template_id": null, "likes": null, "user_reports": [], "saved": false, "id": "ggweua4", "banned_at_utc": null, "mod_reason_title": null, "gilded": 0, "archived": false, "no_follow": true, "author": {"name": "santcg7", "fullname": "t2_4f4gj0gi"}, "can_mod_post": false, "created_utc": 1608819899.0, "send_replies": true, "parent_id": "t1_ggwe79m", "score": 1, "author_fullname": "t2_4f4gj0gi", "report_reasons": null, "approved_by": null, "all_awardings": [], "subreddit_id": "t5_2th52", "body": "Thank you. Will definitely learn those topics.", "edited": false, "author_flair_css_class": null, "is_submitter": false, "downs": 0, "author_flair_richtext": [], "author_patreon_flair": false, "body_html": "<div class=\"md\"><p>Thank you. Will definitely learn those topics.</p>\n</div>", "gildings": {}, "collapsed_reason": null, "associated_award": null, "stickied": false, "author_premium": true, "subreddit_type": "public", "can_gild": true, "top_awarded_type": null, "author_flair_text_color": null, "score_hidden": false, "permalink": "/r/wallstreetbets/comments/kjfpf3/my_first_yolo_what_do_you_guys_think/ggweua4/", "num_reports": null, "locked": false, "name": "t1_ggweua4", "created": 1608848699.0, "author_flair_text": null, "treatment_tags": [], "collapsed": false, "subreddit_name_prefixed": "r/wallstreetbets", "controversiality": 0, "depth": 5, "author_flair_background_color": null, "collapsed_because_crowd_control": null, "mod_reports": [], "mod_note": null, "distinguished": null, "replies": []}]}, {"total_awards_received": 0, "approved_at_utc": null, "comment_type": null, "awarders": [], "mod_reason_by": null, "banned_by": null, "ups": 1, "author_flair_type": "richtext", "removal_reason": null, "link_id": "t3_kjfpf3", "author_flair_template_id": null, "likes": null, "user_reports": [], "saved": false, "id": "ggwdrv3", "banned_at_utc": null, "mod_reason_title": null, "gilded": 0, "archived": false, "no_follow": true, "author": {"name": "abrakadabrakababra", "fullname": "t2_5him47nk"}, "can_mod_post": false, "send_replies": true, "parent_id": "t1_ggwdlkb", "score": 1, "author_fullname": "t2_5him47nk", "report_reasons": null, "approved_by": null, "all_awardings": [], "subreddit_id": "t5_2th52", "collapsed": false, "body": "Sell and roll over to feb", "edited": false, "author_flair_css_class": null, "is_submitter": false, "downs": 0, "author_flair_richtext": [{"e": "text", "t": "\u001b201126:7:2"}], "author_patreon_flair": false, "body_html": "<div class=\"md\"><p>Sell and roll over to feb</p>\n</div>", "gildings": {}, "collapsed_reason": null, "associated_award": null, "stickied": false, "author_premium": false, "subreddit_type": "public", "can_gild": true, "top_awarded_type": null, "author_flair_text_color": "dark", "score_hidden": false, "permalink": "/r/wallstreetbets/comments/kjfpf3/my_first_yolo_what_do_you_guys_think/ggwdrv3/", "num_reports": null, "locked": false, "name": "t1_ggwdrv3", "created": 1608847938.0, "author_flair_text": "\u001b201126:7:2", "treatment_tags": [], "created_utc": 1608819138.0, "subreddit_name_prefixed": "r/wallstreetbets", "controversiality": 0, "depth": 4, "author_flair_background_color": "", "collapsed_because_crowd_control": null, "mod_reports": [], "mod_note": null, "distinguished": null, "replies": []}]}]}, {"total_awards_received": 0, "approved_at_utc": null, "comment_type": null, "awarders": [], "mod_reason_by": null, "banned_by": null, "ups": 1, "author_flair_type": "text", "removal_reason": null, "link_id": "t3_kjfpf3", "author_flair_template_id": null, "likes": null, "user_reports": [], "saved": false, "id": "ggwh0xj", "banned_at_utc": null, "mod_reason_title": null, "gilded": 0, "archived": false, "no_follow": true, "author": {"name": "elijahpcz", "fullname": "t2_327ti0ff"}, "can_mod_post": false, "created_utc": 1608821373.0, "send_replies": true, "parent_id": "t1_ggwc78b", "score": 1, "author_fullname": "t2_327ti0ff", "report_reasons": null, "approved_by": null, "all_awardings": [], "subreddit_id": "t5_2th52", "body": "Sell these and roll them out to some ITM or barely OTM 2023 calls. Buy 3-10 of them (depending on the strike price) instead of 50 of these. Palantir will grow over time, it\u2019s not a pump and dump play. If you roll out to 2023, you\u2019ll also have the option to collect premium, or exercise the shares", "edited": false, "author_flair_css_class": null, "is_submitter": false, "downs": 0, "author_flair_richtext": [], "author_patreon_flair": false, "body_html": "<div class=\"md\"><p>Sell these and roll them out to some ITM or barely OTM 2023 calls. Buy 3-10 of them (depending on the strike price) instead of 50 of these. Palantir will grow over time, it\u2019s not a pump and dump play. If you roll out to 2023, you\u2019ll also have the option to collect premium, or exercise the shares</p>\n</div>", "gildings": {}, "collapsed_reason": null, "associated_award": null, "stickied": false, "author_premium": false, "subreddit_type": "public", "can_gild": true, "top_awarded_type": null, "author_flair_text_color": null, "score_hidden": false, "permalink": "/r/wallstreetbets/comments/kjfpf3/my_first_yolo_what_do_you_guys_think/ggwh0xj/", "num_reports": null, "locked": false, "name": "t1_ggwh0xj", "created": 1608850173.0, "author_flair_text": null, "treatment_tags": [], "collapsed": false, "subreddit_name_prefixed": "r/wallstreetbets", "controversiality": 0, "depth": 2, "author_flair_background_color": null, "collapsed_because_crowd_control": null, "mod_reports": [], "mod_note": null, "distinguished": null, "replies": []}]}]}, {"total_awards_received": 0, "approved_at_utc": null, "comment_type": null, "awarders": [], "mod_reason_by": null, "banned_by": null, "ups": 2, "author_flair_type": "richtext", "removal_reason": null, "link_id": "t3_kjfpf3", "author_flair_template_id": null, "likes": null, "user_reports": [], "saved": false, "id": "ggwbvnd", "banned_at_utc": null, "mod_reason_title": null, "gilded": 0, "archived": false, "no_follow": true, "author": {"name": "TitAList", "fullname": "t2_5j8y16ut"}, "can_mod_post": false, "send_replies": true, "parent_id": "t3_kjfpf3", "score": 2, "author_fullname": "t2_5j8y16ut", "report_reasons": null, "approved_by": null, "all_awardings": [], "subreddit_id": "t5_2th52", "body": "Should print. Holding shares myself", "edited": false, "downs": 0, "author_flair_css_class": null, "is_submitter": false, "collapsed": false, "author_flair_richtext": [{"e": "text", "t": "\u001b201218:2:1"}], "author_patreon_flair": false, "body_html": "<div class=\"md\"><p>Should print. Holding shares myself</p>\n</div>", "gildings": {}, "collapsed_reason": null, "associated_award": null, "stickied": false, "author_premium": false, "subreddit_type": "public", "can_gild": true, "top_awarded_type": null, "author_flair_text_color": "dark", "score_hidden": false, "permalink": "/r/wallstreetbets/comments/kjfpf3/my_first_yolo_what_do_you_guys_think/ggwbvnd/", "num_reports": null, "locked": false, "name": "t1_ggwbvnd", "created": 1608846515.0, "author_flair_text": "\u001b201218:2:1", "treatment_tags": [], "created_utc": 1608817715.0, "subreddit_name_prefixed": "r/wallstreetbets", "controversiality": 0, "depth": 0, "author_flair_background_color": "", "collapsed_because_crowd_control": null, "mod_reports": [], "mod_note": null, "distinguished": null, "replies": [{"total_awards_received": 0, "approved_at_utc": null, "comment_type": null, "awarders": [], "mod_reason_by": null, "banned_by": null, "ups": 1, "author_flair_type": "text", "removal_reason": null, "link_id": "t3_kjfpf3", "author_flair_template_id": null, "likes": null, "user_reports": [], "saved": false, "id": "ggwbxqd", "banned_at_utc": null, "mod_reason_title": null, "gilded": 0, "archived": false, "no_follow": true, "author": {"name": "oxle504", "fullname": "t2_agaw8i9"}, "can_mod_post": false, "send_replies": true, "parent_id": "t1_ggwbvnd", "score": 1, "author_fullname": "t2_agaw8i9", "report_reasons": null, "approved_by": null, "all_awardings": [], "subreddit_id": "t5_2th52", "collapsed": false, "body": "I was almost negative 5k at one point", "edited": false, "author_flair_css_class": null, "is_submitter": true, "downs": 0, "author_flair_richtext": [], "author_patreon_flair": false, "body_html": "<div class=\"md\"><p>I was almost negative 5k at one point</p>\n</div>", "gildings": {}, "collapsed_reason": null, "associated_award": null, "stickied": false, "author_premium": false, "subreddit_type": "public", "can_gild": true, "top_awarded_type": null, "author_flair_text_color": null, "score_hidden": false, "permalink": "/r/wallstreetbets/comments/kjfpf3/my_first_yolo_what_do_you_guys_think/ggwbxqd/", "num_reports": null, "locked": false, "name": "t1_ggwbxqd", "created": 1608846559.0, "author_flair_text": null, "treatment_tags": [], "created_utc": 1608817759.0, "subreddit_name_prefixed": "r/wallstreetbets", "controversiality": 0, "depth": 1, "author_flair_background_color": null, "collapsed_because_crowd_control": null, "mod_reports": [], "mod_note": null, "distinguished": null, "replies": []}]}, {"total_awards_received": 0, "approved_at_utc": null, "comment_type": null, "awarders": [], "mod_reason_by": null, "banned_by": null, "ups": 2, "author_flair_type": "text", "removal_reason": null, "link_id": "t3_kjfpf3", "author_flair_template_id": null, "likes": null, "user_reports": [], "saved": false, "id": "ggwc6dw", "banned_at_utc": null, "mod_reason_title": null, "gilded": 0, "archived": false, "no_follow": true, "author": {"name": "Nuts4Puts", "fullname": "t2_7802gl65"}, "can_mod_post": false, "send_replies": true, "parent_id": "t3_kjfpf3", "score": 2, "author_fullname": "t2_7802gl65", "report_reasons": null, "approved_by": null, "all_awardings": [], "subreddit_id": "t5_2th52", "body": "Demo Day is on the 26th of Jan, might see some movement in price as anticipation ramps up. I\u2019m long too (the stock and the Mar \u201821 $30c).", "edited": false, "downs": 0, "author_flair_css_class": null, "is_submitter": false, "collapsed": false, "author_flair_richtext": [], "author_patreon_flair": false, "body_html": "<div class=\"md\"><p>Demo Day is on the 26th of Jan, might see some movement in price as anticipation ramps up. I\u2019m long too (the stock and the Mar \u201821 $30c).</p>\n</div>", "gildings": {}, "collapsed_reason": null, "associated_award": null, "stickied": false, "author_premium": false, "subreddit_type": "public", "can_gild": true, "top_awarded_type": null, "author_flair_text_color": null, "score_hidden": false, "permalink": "/r/wallstreetbets/comments/kjfpf3/my_first_yolo_what_do_you_guys_think/ggwc6dw/", "num_reports": null, "locked": false, "name": "t1_ggwc6dw", "created": 1608846746.0, "author_flair_text": null, "treatment_tags": [], "created_utc": 1608817946.0, "subreddit_name_prefixed": "r/wallstreetbets", "controversiality": 0, "depth": 0, "author_flair_background_color": null, "collapsed_because_crowd_control": null, "mod_reports": [], "mod_note": null, "distinguished": null, "replies": []}]}